CHANGES.txt
MANIFEST.in
README.md
setup.py
src/django_term_field.egg-info/PKG-INFO
src/django_term_field.egg-info/SOURCES.txt
src/django_term_field.egg-info/dependency_links.txt
src/django_term_field.egg-info/entry_points.txt
src/django_term_field.egg-info/requires.txt
src/django_term_field.egg-info/top_level.txt
src/ex/__init__.py
src/ex/django/__init__.py
src/ex/django/fields.py