Metadata-Version: 1.1
Name: django-term-field
Version: 0.2
Summary: Django term field(with from-to multi value).
Home-page: https://bitbucket.org/imagawa_yakata/django-term-field
Author: imagawa_yakata(oyakata)
Author-email: imagawa.hougikumaru@gmail.com
License: MIT
Platform: UNKNOWN
Classifier: Development Status :: 1 - Planning
Classifier: Intended Audience :: Developers
Classifier: Programming Language :: Python
Classifier: Programming Language :: Python :: 2.7
Classifier: License :: OSI Approved :: MIT License
